setup.py
tkinterDnD/__init__.py
tkinterDnD/dnd.py
tkinterDnD.egg-info/PKG-INFO
tkinterDnD.egg-info/SOURCES.txt
tkinterDnD.egg-info/dependency_links.txt
tkinterDnD.egg-info/requires.txt
tkinterDnD.egg-info/top_level.txt