Metadata-Version: 1.0
Name: tkinterDnD
Version: 0.0.0
Summary: A python tkinter drag and drop system.
Home-page: https://github.com/TechDudie/tkinterDnD
Author: UNKNOWN
Author-email: technologydev101@gmail.com
License: MIT
Platform: any
